codeforces_api/__init__.py
codeforces_api/downloader.py
codeforcess-0.1.0.dist-info/METADATA
codeforcess-0.1.0.dist-info/WHEEL
codeforcess-0.1.0.dist-info/entry_points.txt
codeforcess-0.1.0.dist-info/top_level.txt
codeforcess-0.1.0.dist-info/RECORD
