Metadata-Version: 2.1
Name: codeforcess
Version: 0.1.0
Summary: A package to download all Codeforces problems
Home-page: https://github.com/Sudhir878786/codeforces-api
Author: Sudhir Sharma
Author-email: sudhirsharma@iitbhilai.ac.in
Classifier: Programming Language :: Python :: 3
Classifier: License :: OSI Approved :: MIT License
Classifier: Operating System :: OS Independent
Requires-Python: >=3.6
Requires-Dist: requests
